{"_type":"export","__export_format":4,"__export_date":"2024-04-27T20:56:54.563Z","__export_source":"insomnia.desktop.app:v9.0.0","resources":[{"_id":"req_80c755a83b5b4f34ad3404862a41cf06","parentId":"wrk_6ffc6b4b4f1b47438b75d21905f3e941","modified":1714201559449,"created":1714201527253,"url":"http://localhost:8080/ping","name":"ping","description":"","method":"GET","body":{},"preRequestScript":"","parameters":[],"headers":[{"name":"User-Agent","value":"insomnia/9.0.0"}],"authentication":{},"metaSortKey":-1714201527253,"isPrivate":false,"pathParameters":[],"settingStoreCookies":true,"settingSendCookies":true,"settingDisableRenderRequestBody":false,"settingEncodeUrl":true,"settingRebuildPath":true,"settingFollowRedirects":"global","_type":"request"},{"_id":"wrk_6ffc6b4b4f1b47438b75d21905f3e941","parentId":null,"modified":1714201520607,"created":1714201520607,"name":"challenge-contact","description":"","scope":"collection","_type":"workspace"},{"_id":"req_2b83044fba5e42239c101d9e97ab6ab6","parentId":"wrk_6ffc6b4b4f1b47438b75d21905f3e941","modified":1714205526626,"created":1714205496684,"url":"http://localhost:8080/api/v1/contact/4e197e3f-8ac7-4774-a76d-a18b7e4c6f48","name":"update","description":"","method":"PUT","body":{"mimeType":"application/json","text":"{\n\t  \"email\": \"edited@gmail.com\",\n\t\t\"lastName\": \"Last name - edited\",\n\t\t\"name\": \"name - edited\",\n\t\t\"phoneNumber\": \"11111\"\n}"},"preRequestScript":"","parameters":[],"headers":[{"name":"Content-Type","value":"application/json"},{"name":"User-Agent","value":"insomnia/9.0.0"}],"authentication":{},"metaSortKey":-1714201576391.75,"isPrivate":false,"pathParameters":[],"settingStoreCookies":true,"settingSendCookies":true,"settingDisableRenderRequestBody":false,"settingEncodeUrl":true,"settingRebuildPath":true,"settingFollowRedirects":"global","_type":"request"},{"_id":"req_0720aa197eca4126a52a998ee1b81743","parentId":"wrk_6ffc6b4b4f1b47438b75d21905f3e941","modified":1714204353174,"created":1714203151342,"url":"http://localhost:8080/api/v1/contact","name":"create","description":"","method":"POST","body":{"mimeType":"application/json","text":"{\n\t  \"email\": \"theemail@gmail.com\",\n\t\t\"lastName\": \"Last name\",\n\t\t\"name\": \"name\",\n\t\t\"phoneNumber\": \"3333333333\"\n}"},"preRequestScript":"","parameters":[],"headers":[{"name":"Content-Type","value":"application/json"},{"name":"User-Agent","value":"insomnia/9.0.0"}],"authentication":{},"metaSortKey":-1714201625530.5,"isPrivate":false,"pathParameters":[],"settingStoreCookies":true,"settingSendCookies":true,"settingDisableRenderRequestBody":false,"settingEncodeUrl":true,"settingRebuildPath":true,"settingFollowRedirects":"global","_type":"request"},{"_id":"req_e005186d5214412486575b900dd058d8","parentId":"wrk_6ffc6b4b4f1b47438b75d21905f3e941","modified":1714204859678,"created":1714204801789,"url":"http://localhost:8080/api/v1/contact/4e166a6c-f843-485f-9430-f4d9d46bc0cf","name":"delete","description":"","method":"DELETE","body":{},"preRequestScript":"","parameters":[],"headers":[{"name":"User-Agent","value":"insomnia/9.0.0"}],"authentication":{},"metaSortKey":-1714201674669.25,"isPrivate":false,"pathParameters":[],"settingStoreCookies":true,"settingSendCookies":true,"settingDisableRenderRequestBody":false,"settingEncodeUrl":true,"settingRebuildPath":true,"settingFollowRedirects":"global","_type":"request"},{"_id":"req_10bd5de611d24067a655ca3d6aaabc60","parentId":"wrk_6ffc6b4b4f1b47438b75d21905f3e941","modified":1714205485754,"created":1714201723808,"url":"http://localhost:8080/api/v1/contact/4e197e3f-8ac7-4774-a76d-a18b7e4c6f48","name":"get by id","description":"","method":"GET","body":{},"preRequestScript":"","parameters":[],"headers":[{"name":"User-Agent","value":"insomnia/9.0.0"}],"authentication":{},"metaSortKey":-1714201723808,"isPrivate":false,"pathParameters":[],"settingStoreCookies":true,"settingSendCookies":true,"settingDisableRenderRequestBody":false,"settingEncodeUrl":true,"settingRebuildPath":true,"settingFollowRedirects":"global","_type":"request"},{"_id":"env_baea85230b9edf9604d287f50d1d72f91004b028","parentId":"wrk_6ffc6b4b4f1b47438b75d21905f3e941","modified":1714201520609,"created":1714201520609,"name":"Base Environment","data":{},"dataPropertyOrder":null,"color":null,"isPrivate":false,"metaSortKey":1714201520610,"_type":"environment"},{"_id":"jar_baea85230b9edf9604d287f50d1d72f91004b028","parentId":"wrk_6ffc6b4b4f1b47438b75d21905f3e941","modified":1714201520611,"created":1714201520611,"name":"Default Jar","cookies":[],"_type":"cookie_jar"}]}